[
  {
    "alliance": "NHI",
    "player": "}nobita45 Warzone nobi #",
    "warzone": 1307,
    "kill_score": 1307,
    "group": "C",
    "rank": 1
  },
  {
    "alliance": "aResjLadyD Warzone aREs",
    "player": "LadyDragus #",
    "warzone": 1304,
    "kill_score": 1304,
    "group": "C",
    "rank": 2
  },
  {
    "alliance": "FIND",
    "player": "Warzone QAK]Caesar oak ASA #",
    "warzone": 1301,
    "kill_score": 1303,
    "group": "C",
    "rank": 3
  },
  {
    "alliance": "FIND",
    "player": "Warzone ABA #",
    "warzone": 1303,
    "kill_score": 1303,
    "group": "C",
    "rank": 4
  },
  {
    "alliance": "TQAK",
    "player": "Caesar",
    "warzone": 1301,
    "kill_score": 1301,
    "group": "C",
    "rank": 5
  }
]